{
 "version": 1,
 "char": "*",
 "codepoint": 42,
 "provenance": "traced",
 "trace": {
  "corpus": "gelsons.refined.npz",
  "samples": 15,
  "consensusHash": "77bfb0c718fa",
  "date": "2026-07-19"
 },
 "width": 749.1,
 "baselineNudgePx": 0,
 "overrides": {},
 "strokes": [
  {
   "closed": false,
   "nodes": [
    {
     "x": 582.9,
     "y": 422.2,
     "type": "corner"
    },
    {
     "x": 527.5038086794251,
     "y": 486.3,
     "type": "corner"
    },
    {
     "x": 498.3,
     "y": 486.3,
     "type": "corner"
    }
   ]
  },
  {
   "closed": false,
   "nodes": [
    {
     "x": 544.0,
     "y": 660.9,
     "type": "corner"
    },
    {
     "x": 544.0,
     "y": 586.5669549452173,
     "type": "corner"
    },
    {
     "x": 562.4,
     "y": 566.7,
     "type": "corner"
    }
   ]
  },
  {
   "closed": false,
   "nodes": [
    {
     "x": 32.9,
     "y": 660.9,
     "type": "corner"
    },
    {
     "x": 50.8,
     "y": 660.9,
     "type": "corner"
    },
    {
     "x": 50.8,
     "y": 660.9,
     "type": "corner"
    }
   ]
  },
  {
   "closed": false,
   "nodes": [
    {
     "x": 699.6,
     "y": 660.9,
     "type": "corner",
     "hOut": {
      "x": 649.4333191205158,
      "y": 600.3
     }
    },
    {
     "x": 510.7,
     "y": 542.1,
     "type": "corner",
     "hIn": {
      "x": 580.6715081954634,
      "y": 575.393986491459
     }
    }
   ]
  },
  {
   "closed": false,
   "nodes": [
    {
     "x": 716.2,
     "y": 272.2,
     "type": "corner"
    },
    {
     "x": 648.336599681882,
     "y": 317.3,
     "type": "corner"
    },
    {
     "x": 610.7,
     "y": 317.3,
     "type": "corner"
    }
   ]
  },
  {
   "closed": false,
   "nodes": [
    {
     "x": 510.7,
     "y": 542.1,
     "type": "corner",
     "hOut": {
      "x": 436.7392997765187,
      "y": 546.5010066070575
     }
    },
    {
     "x": 223.113810697761,
     "y": 660.9,
     "type": "corner",
     "hIn": {
      "x": 255.3235538334736,
      "y": 582.7
     }
    },
    {
     "x": 52.3,
     "y": 660.9,
     "type": "corner"
    }
   ]
  },
  {
   "closed": false,
   "nodes": [
    {
     "x": 366.2,
     "y": 319.4,
     "type": "corner"
    },
    {
     "x": 399.4695266305966,
     "y": 330.21614278182926,
     "type": "corner",
     "hOut": {
      "x": 558.5870088864177,
      "y": 418.8695292780684
     }
    },
    {
     "x": 477.29999999999995,
     "y": 783.2999999999998,
     "type": "corner",
     "hIn": {
      "x": 470.49147575808934,
      "y": 640.1306060875178
     }
    }
   ]
  }
 ]
}