{
 "version": 1,
 "char": "B",
 "codepoint": 66,
 "provenance": "traced",
 "trace": {
  "corpus": "sprouts.samples.npz",
  "samples": 33,
  "consensusHash": "6200c5012b39",
  "date": "2026-07-07"
 },
 "width": 562.9,
 "baselineNudgePx": 0,
 "overrides": {},
 "strokes": [
  {
   "closed": false,
   "nodes": [
    {
     "x": 39.8,
     "y": 461.1,
     "type": "corner"
    },
    {
     "x": 93.9,
     "y": 461.1,
     "type": "corner"
    }
   ]
  },
  {
   "closed": false,
   "nodes": [
    {
     "x": 117.5,
     "y": 45.8,
     "type": "corner"
    },
    {
     "x": 167.10352462598584,
     "y": 45.8,
     "type": "corner",
     "hOut": {
      "x": 263.47572183102307,
      "y": 93.2
     }
    },
    {
     "x": 392.5,
     "y": 45.8,
     "type": "corner",
     "hIn": {
      "x": 285.294874756214,
      "y": 45.8
     }
    }
   ]
  },
  {
   "closed": false,
   "nodes": [
    {
     "x": 377.7,
     "y": 954.2,
     "type": "corner"
    },
    {
     "x": 377.7,
     "y": 954.2,
     "type": "corner"
    },
    {
     "x": 241.01999108847502,
     "y": 954.2,
     "type": "corner",
     "hOut": {
      "x": 197.36022791259782,
      "y": 962.8
     }
    },
    {
     "x": 130.1,
     "y": 954.2,
     "type": "corner",
     "hIn": {
      "x": 186.01786888953148,
      "y": 921.7
     }
    }
   ]
  },
  {
   "closed": false,
   "nodes": [
    {
     "x": 421.7,
     "y": 525.0,
     "type": "corner"
    },
    {
     "x": 113.4,
     "y": 525.0,
     "type": "corner"
    }
   ]
  },
  {
   "closed": false,
   "nodes": [
    {
     "x": 506.4,
     "y": 244.4,
     "type": "corner"
    },
    {
     "x": 399.8,
     "y": 45.8,
     "type": "corner"
    }
   ]
  },
  {
   "closed": false,
   "nodes": [
    {
     "x": 117.5,
     "y": 45.8,
     "type": "corner",
     "hOut": {
      "x": 123.45815583896332,
      "y": 356.9
     }
    },
    {
     "x": 130.10000000000002,
     "y": 954.2,
     "type": "corner",
     "hIn": {
      "x": 68.40608185543158,
      "y": 641.8
     }
    }
   ]
  },
  {
   "closed": false,
   "nodes": [
    {
     "x": 466.6,
     "y": 654.2,
     "type": "corner",
     "hOut": {
      "x": 524.4076868578212,
      "y": 748.1
     }
    },
    {
     "x": 381.4,
     "y": 954.2,
     "type": "corner",
     "hIn": {
      "x": 424.5521527111609,
      "y": 874.6
     }
    }
   ]
  },
  {
   "closed": false,
   "nodes": [
    {
     "x": 439.8,
     "y": 654.2,
     "type": "corner",
     "hOut": {
      "x": 421.1082831248482,
      "y": 506.1
     }
    },
    {
     "x": 523.1,
     "y": 333.3,
     "type": "corner",
     "hIn": {
      "x": 456.30231604724094,
      "y": 458.77132526261573
     }
    }
   ]
  }
 ]
}
