{
 "version": 1,
 "char": "1",
 "codepoint": 49,
 "provenance": "traced",
 "trace": {
  "corpus": "sprouts.samples.npz",
  "samples": 84,
  "consensusHash": "a89b7838c33e",
  "date": "2026-07-07"
 },
 "width": 262.0,
 "baselineNudgePx": 0,
 "overrides": {},
 "strokes": [
  {
   "closed": false,
   "nodes": [
    {
     "x": 170.7,
     "y": 963.5,
     "type": "corner"
    },
    {
     "x": 139.3,
     "y": 858.3,
     "type": "corner"
    }
   ]
  },
  {
   "closed": false,
   "nodes": [
    {
     "x": 39.3,
     "y": 857.0,
     "type": "corner"
    },
    {
     "x": 139.3,
     "y": 857.0,
     "type": "corner"
    }
   ]
  },
  {
   "closed": false,
   "nodes": [
    {
     "x": 222.7,
     "y": 877.8,
     "type": "corner"
    },
    {
     "x": 170.7,
     "y": 963.5,
     "type": "corner"
    }
   ]
  },
  {
   "closed": false,
   "nodes": [
    {
     "x": 170.7,
     "y": 963.5,
     "type": "corner"
    },
    {
     "x": 179.72104597707954,
     "y": 963.5,
     "type": "corner",
     "hOut": {
      "x": 177.85142676777951,
      "y": 989.6
     }
    },
    {
     "x": 172.35698006217189,
     "y": 864.2974670552892,
     "type": "smooth",
     "hIn": {
      "x": 170.70893855398475,
      "y": 883.2755050297051
     },
     "hOut": {
      "x": 179.91030767132247,
      "y": 792.3421183725369
     }
    },
    {
     "x": 194.18761766845438,
     "y": 663.5,
     "type": "smooth",
     "hIn": {
      "x": 189.76854426133275,
      "y": 735.7
     },
     "hOut": {
      "x": 207.66460667936542,
      "y": 459.4
     }
    },
    {
     "x": 183.8,
     "y": 36.5,
     "type": "corner",
     "hIn": {
      "x": 187.18109182545356,
      "y": 240.5
     }
    }
   ]
  }
 ]
}
